{
    "DateOfJoin": "12-06-11",
    "Enddate": "",
    "Grade": "SE.07",
    "Ccc": "D1729",
    "EmployeeName": "Andrew Muten",
    "RollNo": "00000",
    "Position": "SENIOR SOFTWARE ENGINEER",
    "Organisation": "Product Engineering AAT",
    "BusinessGroupId": 61,
    "HiredDate": "12-06-11",
    "IsRetiree": false,
    "TermDate": "",
    "LastSuccessAttempt": "Never",
    "LastFailedAttempt": "Never",
    "AnnualDestination": "LAHORE",
    "MaritalStatus": "Married",
    "CCSection": "EMIRATES GROUP I T",
    "NewCostCenter": "17029",
    "EkWaiver": "No",
    "Remarks": "",
    "HRText": "",
    "IsOSStaff": false,
    "IsOSAdmin": null,
    "IsOSRetiree": null,
    "IsConsultant": null,
    "IsMercatorConsultant": null,
    "User_Role": null
  }